README.md
setup.cfg
setup.py
aioimgur/__init__.py
aioimgur/client.py
aioimgur.egg-info/PKG-INFO
aioimgur.egg-info/SOURCES.txt
aioimgur.egg-info/dependency_links.txt
aioimgur.egg-info/requires.txt
aioimgur.egg-info/top_level.txt
aioimgur/helpers/__init__.py
aioimgur/helpers/error.py
aioimgur/helpers/format.py
aioimgur/imgur/__init__.py
aioimgur/imgur/models/__init__.py
aioimgur/imgur/models/account.py
aioimgur/imgur/models/account_settings.py
aioimgur/imgur/models/album.py
aioimgur/imgur/models/comment.py
aioimgur/imgur/models/conversation.py
aioimgur/imgur/models/custom_gallery.py
aioimgur/imgur/models/gallery_album.py
aioimgur/imgur/models/gallery_image.py
aioimgur/imgur/models/image.py
aioimgur/imgur/models/message.py
aioimgur/imgur/models/notification.py
aioimgur/imgur/models/tag.py
aioimgur/imgur/models/tag_vote.py